greas3/VERSION
greas3/__init__.py
greas3/__main__.py
greas3/check.py
greas3/logging.py
greas3/operations.py
greas3/put_operation.py
greas3/put_operations.py
greas3/py.typed
greas3/cli/__init__.py
greas3/cli/greas3_cli.py
greas3/cli/greas3_task.py
greas3/cli/paths_args.py
greas3/cli/py.typed
greas3-1.0.0b2.dist-info/LICENSE
greas3-1.0.0b2.dist-info/METADATA
greas3-1.0.0b2.dist-info/WHEEL
greas3-1.0.0b2.dist-info/entry_points.txt
greas3-1.0.0b2.dist-info/top_level.txt
greas3-1.0.0b2.dist-info/RECORD
