Metadata-Version: 2.1
Name: greas3
Version: 1.0.0b2
Summary: Synchronises S3 buckets with local directories
Home-page: https://github.com/cariad/greas3
Author: Cariad Eccleston
Author-email: cariad@cariad.earth
License: MIT
Classifier: Development Status :: 4 - Beta
Classifier: License :: OSI Approved :: MIT License
Classifier: Natural Language :: English
Classifier: Operating System :: OS Independent
Classifier: Programming Language :: Python :: 3 :: Only
Classifier: Programming Language :: Python :: 3.10
Classifier: Programming Language :: Python :: 3.11
Classifier: Programming Language :: Python :: 3.9
Classifier: Typing :: Typed
Requires-Python: >=3.9
License-File: LICENSE
Requires-Dist: ansiscape (~=1.0)
Requires-Dist: boto3 (~=1.0)
Requires-Dist: checksome (~=1.0)
Requires-Dist: cline (~=1.0)
Requires-Dist: slash3 (~=1.0)
